pycronofy/__init__.py
pycronofy/auth.py
pycronofy/batch.py
pycronofy/client.py
pycronofy/datetime_utils.py
pycronofy/exceptions.py
pycronofy/pagination.py
pycronofy/request_handler.py
pycronofy/settings.py
pycronofy/validation.py
pycronofy/tests/common_data.py
pycronofy/tests/test_application_calendar.py
pycronofy/tests/test_auth.py
pycronofy/tests/test_availability.py
pycronofy/tests/test_batch.py
pycronofy/tests/test_client.py
pycronofy/tests/test_conferencing_services.py
pycronofy/tests/test_custom_datacenter.py
pycronofy/tests/test_datetime_utils.py
pycronofy/tests/test_pagination.py
pycronofy/tests/test_real_time_scheduling.py
pycronofy/tests/test_real_time_sequencing.py
pycronofy/tests/test_request_handler.py
pycronofy/tests/test_validation.py
PyCronofy-2.0.7.dist-info/LICENCE.txt
PyCronofy-2.0.7.dist-info/METADATA
PyCronofy-2.0.7.dist-info/WHEEL
PyCronofy-2.0.7.dist-info/top_level.txt
PyCronofy-2.0.7.dist-info/RECORD
