Metadata-Version: 2.1
Name: PyCronofy
Version: 2.0.7
Summary: Python library for Cronofy
Author-email: VenueBook <dev@venuebook.com>, Cronofy <support@cronofy.com>
Project-URL: Homepage, https://github.com/cronofy/pycronofy
Project-URL: API Docs, https://docs.cronofy.com/developers/
Classifier: Development Status :: 5 - Production/Stable
Classifier: Intended Audience :: Developers
Classifier: License :: OSI Approved :: MIT License
Classifier: Natural Language :: English
Classifier: Operating System :: OS Independent
Classifier: Programming Language :: Python :: 3
Classifier: Topic :: Software Development :: Libraries :: Python Modules
Requires-Python: >=3.7
License-File: LICENCE.txt
Requires-Dist: requests >=2.20.0
Requires-Dist: pytz >=2013.7
